mir/sre/__init__.py
mir.sre-0.1.0.dist-info/DESCRIPTION.rst
mir.sre-0.1.0.dist-info/METADATA
mir.sre-0.1.0.dist-info/RECORD
mir.sre-0.1.0.dist-info/WHEEL
mir.sre-0.1.0.dist-info/metadata.json
mir.sre-0.1.0.dist-info/top_level.txt
