Metadata-Version: 2.0
Name: mir.sre
Version: 0.1.0
Summary: Structural regular expressions
Home-page: https://github.com/darkfeline/mir.sre
Author: Allen Li
Author-email: darkfeline@felesatra.moe
License: UNKNOWN
Platform: UNKNOWN
Classifier: Development Status :: 4 - Beta
Classifier: Intended Audience :: Developers
Classifier: License :: OSI Approved :: Apache Software License
Classifier: Programming Language :: Python :: 3.6
